<theme>
	<formatVersion>4</formatVersion>

	<view name="system">
		<text name="info1" extra="true">
			<text>Sega NAOMI 2 é uma placa de fliperama desenvolvida pela Sega e é sucessora do hardware Sega NAOMI. Foi originalmente lançado em 2000. Como usa arquitetura NAOMI semelhante (mas significativamente aprimorada), também é totalmente compatível com seu antecessor.</text>
		</text>

		<text name="info1" extra="true" region="PTBR">
			<text>Sega NAOMI 2 é uma placa de fliperama desenvolvida pela Sega e é sucessora do hardware Sega NAOMI. Foi originalmente lançado em 2000. Como usa arquitetura NAOMI semelhante (mas significativamente aprimorada), também é totalmente compatível com seu antecessor.</text>
		</text>
		
				<text name="info1" extra="true" region="EN">
			<text>Sega NAOMI 2 is an arcade board developed by Sega and is a successor to Sega NAOMI hardware. It was originally released in 2000. Since it uses similar NAOMI architecture (but significantly beefed up), it is also fully backwards compatible with its predecessor.</text>
		</text>
		
				<text name="info1" extra="true" region="ES">
			<text>Sega NAOMI 2 es un tablero arcade desarrollado por Sega y es el sucesor del hardware Sega NAOMI. Fue lanzado originalmente en 2000. Dado que utiliza una arquitectura NAOMI similar (pero significativamente reforzada), también es totalmente compatible con su predecesor.</text>
		</text>
		
				<text name="info1" extra="true" region="FR">
			<text>Sega NAOMI 2 est une carte d'arcade développée par Sega et succède au matériel Sega NAOMI. Puisqu'il utilise une architecture NAOMI similaire (mais considérablement renforcée), il est également entièrement rétrocompatible avec son prédécesseur.</text>
		</text>
		
		<text name="info2" extra="true">
			<text>Sega NAOMI 2</text>
		</text>
		
		<text name="info3" extra="true">
			<text>2000</text>
		</text>
		
		<text name="info4" extra="true">
			<text>SEGA</text>
		</text>			
	</view>
</theme>
